lick/__init__.py
lick/_interpolation.py
lick/_typing.py
lick/lick.py
lick/py.typed
lick-0.9.0.dist-info/licenses/LICENSE
lick-0.9.0.dist-info/WHEEL
lick-0.9.0.dist-info/METADATA
lick-0.9.0.dist-info/RECORD
