Metadata-Version: 2.4
Name: lick
Version: 0.9.0
Summary: A high level Line Integral Convolution (LIC) library, including post-processing and visualization
Author: G. Wafflard-Fernandez, C.M.T. Robert
Requires-Python: >=3.10
License-Expression: GPL-3.0-only
Classifier: Framework :: Matplotlib
Classifier: Programming Language :: Python :: 3
Classifier: Programming Language :: Python :: 3.10
Classifier: Programming Language :: Python :: 3.11
Classifier: Programming Language :: Python :: 3.12
Classifier: Programming Language :: Python :: 3.13
Classifier: Programming Language :: Python :: 3.14
Classifier: Programming Language :: Python :: Implementation :: CPython
Classifier: Topic :: Scientific/Engineering :: Visualization
Classifier: Typing :: Typed
License-File: LICENSE
Requires-Dist: matplotlib>=3.5.0
Requires-Dist: numpy>=1.22, <3
Requires-Dist: rlic>=0.2.1
Requires-Dist: scipy>=1.7.2
Project-URL: Homepage, https://github.com/la-niche/lick
